huawei_lte_api/ApiGroup.py
huawei_lte_api/AuthorizedConnection.py
huawei_lte_api/Client.py
huawei_lte_api/Connection.py
huawei_lte_api/__init__.py
huawei_lte_api/exceptions.py
huawei_lte_api/api/Cradle.py
huawei_lte_api/api/DDns.py
huawei_lte_api/api/Device.py
huawei_lte_api/api/Dhcp.py
huawei_lte_api/api/Diagnosis.py
huawei_lte_api/api/DialUp.py
huawei_lte_api/api/FileManager.py
huawei_lte_api/api/Global.py
huawei_lte_api/api/Host.py
huawei_lte_api/api/Language.py
huawei_lte_api/api/Monitoring.py
huawei_lte_api/api/Net.py
huawei_lte_api/api/OnlineUpdate.py
huawei_lte_api/api/Ota.py
huawei_lte_api/api/Pb.py
huawei_lte_api/api/Pin.py
huawei_lte_api/api/Redirection.py
huawei_lte_api/api/SNtp.py
huawei_lte_api/api/Security.py
huawei_lte_api/api/Sms.py
huawei_lte_api/api/User.py
huawei_lte_api/api/VSim.py
huawei_lte_api/api/WLan.py
huawei_lte_api/api/WebServer.py
huawei_lte_api/api/__init__.py
huawei_lte_api/config/Global.py
huawei_lte_api/config/PcAssistant.py
huawei_lte_api/config/Voice.py
huawei_lte_api/config/__init__.py
huawei_lte_api/enums/__init__.py
huawei_lte_api/enums/client.py
huawei_lte_api/enums/device.py
huawei_lte_api/enums/sms.py
huawei_lte_api/enums/user.py
huawei_lte_api/enums/wlan.py
huawei_lte_api-1.0.8.dist-info/DESCRIPTION.rst
huawei_lte_api-1.0.8.dist-info/METADATA
huawei_lte_api-1.0.8.dist-info/RECORD
huawei_lte_api-1.0.8.dist-info/WHEEL
huawei_lte_api-1.0.8.dist-info/metadata.json
huawei_lte_api-1.0.8.dist-info/top_level.txt
